jsonpath/__about__.py
jsonpath/__init__.py
jsonpath/__main__.py
jsonpath/_data.py
jsonpath/_types.py
jsonpath/cli.py
jsonpath/env.py
jsonpath/exceptions.py
jsonpath/filter.py
jsonpath/fluent_api.py
jsonpath/lex.py
jsonpath/lru_cache.py
jsonpath/match.py
jsonpath/parse.py
jsonpath/patch.py
jsonpath/path.py
jsonpath/pointer.py
jsonpath/py.typed
jsonpath/segments.py
jsonpath/selectors.py
jsonpath/serialize.py
jsonpath/stream.py
jsonpath/token.py
jsonpath/unescape.py
jsonpath/function_extensions/__init__.py
jsonpath/function_extensions/_pattern.py
jsonpath/function_extensions/arguments.py
jsonpath/function_extensions/count.py
jsonpath/function_extensions/filter_function.py
jsonpath/function_extensions/is_instance.py
jsonpath/function_extensions/keys.py
jsonpath/function_extensions/length.py
jsonpath/function_extensions/match.py
jsonpath/function_extensions/search.py
jsonpath/function_extensions/starts_with.py
jsonpath/function_extensions/typeof.py
jsonpath/function_extensions/value.py
python_jsonpath-2.0.2.dist-info/METADATA
python_jsonpath-2.0.2.dist-info/WHEEL
python_jsonpath-2.0.2.dist-info/entry_points.txt
python_jsonpath-2.0.2.dist-info/licenses/LICENSE.txt
python_jsonpath-2.0.2.dist-info/RECORD
