Metadata-Version: 2.4
Name: python-jsonpath
Version: 2.0.2
Summary: JSONPath, JSON Pointer and JSON Patch for Python.
Project-URL: Documentation, https://jg-rp.github.io/python-jsonpath/
Project-URL: Issues, https://github.com/jg-rp/python-jsonpath/issues
Project-URL: Source, https://github.com/jg-rp/python-jsonpath
Author-email: James Prior <jamesgr.prior@gmail.com>
License-Expression: MIT
License-File: LICENSE.txt
Keywords: JSON,JSON Patch,JSON Path,JSON Pointer,JSONPath,RFC 9535
Classifier: Development Status :: 5 - Production/Stable
Classifier: Intended Audience :: Developers
Classifier: License :: OSI Approved :: MIT License
Classifier: Programming Language :: Python
Classifier: Programming Language :: Python :: 3.8
Classifier: Programming Language :: Python :: 3.9
Classifier: Programming Language :: Python :: 3.10
Classifier: Programming Language :: Python :: 3.11
Classifier: Programming Language :: Python :: 3.12
Classifier: Programming Language :: Python :: 3.13
Classifier: Programming Language :: Python :: 3.14
Classifier: Programming Language :: Python :: Implementation :: CPython
Classifier: Programming Language :: Python :: Implementation :: PyPy
Requires-Python: >=3.8
Provides-Extra: strict
Requires-Dist: iregexp-check>=0.1.4; extra == 'strict'
Requires-Dist: regex; extra == 'strict'
